{"cameraMode":{"drawMode":0,"name":"Shaded","section":"Shading Mode"},"sceneLighting":false,"audioPlay":false,"sceneViewState":{"m_AlwaysRefresh":false,"showFog":true,"showSkybox":true,"showFlares":true,"showImageEffects":true,"showParticleSystems":true,"showVisualEffectGraphs":true,"m_FxEnabled":true},"in2DMode":false,"pivot":{"x":10.66695785522461,"y":6.127488613128662,"z":-3.2999446392059328},"rotation":{"x":-0.3320517838001251,"y":0.2924216389656067,"z":-0.1090020015835762,"w":-0.8902093768119812},"size":1.1660254001617432,"orthographic":false}